odoo/addons/hr_appraisal_oca/README.rst
odoo/addons/hr_appraisal_oca/__init__.py
odoo/addons/hr_appraisal_oca/__manifest__.py
odoo/addons/hr_appraisal_oca/data/mail_activity_type_data.xml
odoo/addons/hr_appraisal_oca/data/mail_template_data.xml
odoo/addons/hr_appraisal_oca/i18n/es.po
odoo/addons/hr_appraisal_oca/i18n/hr_appraisal_oca.pot
odoo/addons/hr_appraisal_oca/i18n/it.po
odoo/addons/hr_appraisal_oca/models/__init__.py
odoo/addons/hr_appraisal_oca/models/hr_appraisal.py
odoo/addons/hr_appraisal_oca/models/hr_appraisal_tag.py
odoo/addons/hr_appraisal_oca/models/hr_appraisal_template.py
odoo/addons/hr_appraisal_oca/models/hr_employee.py
odoo/addons/hr_appraisal_oca/readme/CONTRIBUTORS.md
odoo/addons/hr_appraisal_oca/readme/DESCRIPTION.md
odoo/addons/hr_appraisal_oca/readme/USAGE.md
odoo/addons/hr_appraisal_oca/security/hr_appraisal_security.xml
odoo/addons/hr_appraisal_oca/security/ir.model.access.csv
odoo/addons/hr_appraisal_oca/static/description/banner.png
odoo/addons/hr_appraisal_oca/static/description/icon.png
odoo/addons/hr_appraisal_oca/static/description/index.html
odoo/addons/hr_appraisal_oca/tests/__init__.py
odoo/addons/hr_appraisal_oca/tests/test_hr_appraisal.py
odoo/addons/hr_appraisal_oca/views/hr_appraisal_form_view.xml
odoo/addons/hr_appraisal_oca/views/hr_appraisal_tag_form_view.xml
odoo/addons/hr_appraisal_oca/views/hr_appraisal_template_form_view.xml
odoo/addons/hr_appraisal_oca/views/hr_employee_form_view.xml
odoo/addons/hr_appraisal_oca/wizard/__init__.py
odoo/addons/hr_appraisal_oca/wizard/hr_appraisal_request_wizard_view.xml
odoo/addons/hr_appraisal_oca/wizard/hr_appraisal_wizard.py
odoo/addons/hr_appraisal_oca/wizard/hr_appraisal_wizard_form_view.xml
odoo/addons/hr_appraisal_oca/wizard/res_config_settings.py
odoo/addons/hr_appraisal_oca/wizard/res_config_settings_views.xml
odoo/addons/hr_appraisal_oca/wizard/send_mail_with_template_wizard.py
odoo_addon_hr_appraisal_oca-18.0.1.0.2.1.dist-info/METADATA
odoo_addon_hr_appraisal_oca-18.0.1.0.2.1.dist-info/WHEEL
odoo_addon_hr_appraisal_oca-18.0.1.0.2.1.dist-info/top_level.txt
odoo_addon_hr_appraisal_oca-18.0.1.0.2.1.dist-info/RECORD
