Metadata-Version: 2.1
Name: odoo-addon-hr_appraisal_oca
Version: 18.0.1.0.2.1
Requires-Python: >=3.10
Requires-Dist: odoo==18.0.*
Summary: Module for managing employee appraisals
Home-page: https://github.com/OCA/hr
License: AGPL-3
Author: =?utf-8?q?Fundaci=C3=B3n_Esment=2C_Odoo_Community_Association_=28OCA=29?=
Author-email: support@odoo-community.org
Classifier: Programming Language :: Python
Classifier: Framework :: Odoo
Classifier: Framework :: Odoo :: 18.0
Classifier: License :: OSI Approved :: GNU Affero General Public License v3
